AUTHORS.txt
CHANGES.rst
CLASSIFIERS.txt
LICENSE
MANIFEST.in
README.rst
REQUIREMENTS.txt
setup.py
piwigo/__init__.py
piwigo/__init__.pyc
piwigo/ws.py
piwigo/ws.pyc
piwigo.egg-info/PKG-INFO
piwigo.egg-info/SOURCES.txt
piwigo.egg-info/dependency_links.txt
piwigo.egg-info/requires.txt
piwigo.egg-info/top_level.txt